README.rst
setup.py
helloMyName/__init__.py
helloMyName/welcome.py
helloMyname.egg-info/PKG-INFO
helloMyname.egg-info/SOURCES.txt
helloMyname.egg-info/dependency_links.txt
helloMyname.egg-info/not-zip-safe
helloMyname.egg-info/top_level.txt