Metadata-Version: 1.1
Name: helloMyname
Version: 0.2
Summary: Python package example
Home-page: http://mywebsite
Author: myname
Author-email: tuora@students.wwu.edu
License: none
Keywords: Package Distribution
Platform: UNKNOWN
Classifier: Programming Language :: Python
